langgraph/checkpoint/py.typed
langgraph/checkpoint/sqlite/__init__.py
langgraph/checkpoint/sqlite/aio.py
langgraph/checkpoint/sqlite/utils.py
gigagraph_checkpoint_sqlite-1.0.3.dist-info/METADATA
gigagraph_checkpoint_sqlite-1.0.3.dist-info/WHEEL
gigagraph_checkpoint_sqlite-1.0.3.dist-info/RECORD
