Metadata-Version: 2.1
Name: gigagraph-checkpoint-sqlite
Version: 1.0.3
Summary: Library with a SQLite implementation of LangGraph checkpoint saver.
Home-page: https://github.com/ai-forever/gigagraph
License: MIT
Requires-Python: >=3.9.0,<4.0.0
Classifier: License :: OSI Approved :: MIT License
Classifier: Programming Language :: Python :: 3
Classifier: Programming Language :: Python :: 3.9
Classifier: Programming Language :: Python :: 3.10
Classifier: Programming Language :: Python :: 3.11
Classifier: Programming Language :: Python :: 3.12
Requires-Dist: aiosqlite (>=0.20.0,<0.21.0)
Requires-Dist: gigagraph-checkpoint (>=1.0.8,<2.0.0)
Project-URL: Repository, https://github.com/ai-forever/gigagraph
